SparseArray/__init__.py
SparseArray/sparse_array.c
SparseArray/sparse_array.pxd
SparseArray/sparse_array.pyd
SparseArray/sparse_array.pyx
SparseArray/tests/test_sparse_array.py
SparseArray-0.8.16.dist-info/LICENSE
SparseArray-0.8.16.dist-info/METADATA
SparseArray-0.8.16.dist-info/WHEEL
SparseArray-0.8.16.dist-info/top_level.txt
SparseArray-0.8.16.dist-info/RECORD
